__init__.py
dropgrad/__init__.py
dropgrad/dropgrad_opt.py
test/__init__.py
test/test.py
dropgrad-0.1.0.dist-info/LICENSE
dropgrad-0.1.0.dist-info/METADATA
dropgrad-0.1.0.dist-info/WHEEL
dropgrad-0.1.0.dist-info/top_level.txt
dropgrad-0.1.0.dist-info/RECORD
